ashborn/__init__.py
ashborn/main.py
ashborn/data/ML TS XAI HC/HC/1. Exploratory Data Analysis.ipynb
ashborn/data/ML TS XAI HC/HC/2. Image Analysis.ipynb
ashborn/data/ML TS XAI HC/HC/3 (A). Extraction of Structured Data.ipynb
ashborn/data/ML TS XAI HC/HC/3 (B). Extraction of Unstructured Data.ipynb
ashborn/data/ML TS XAI HC/HC/4. Data Mining on Non Clinical Data.ipynb
ashborn/data/ML TS XAI HC/HC/5. Natural Language Processing.ipynb
ashborn/data/ML TS XAI HC/HC/data/diabetes.csv
ashborn/data/ML TS XAI HC/HC/data/lung.jpeg
ashborn/data/ML TS XAI HC/ML/1. PCA - EDA.ipynb
ashborn/data/ML TS XAI HC/ML/2. KNN Classifier.ipynb
ashborn/data/ML TS XAI HC/ML/3. Linear Discriminant Analysis.ipynb
ashborn/data/ML TS XAI HC/ML/4. Linear Regression.ipynb
ashborn/data/ML TS XAI HC/ML/5. Logistic Regression.ipynb
ashborn/data/ML TS XAI HC/ML/6. Bayesian Classifier.ipynb
ashborn/data/ML TS XAI HC/ML/data/balance-scale.csv
ashborn/data/ML TS XAI HC/ML/data/balance-scale.txt
ashborn/data/ML TS XAI HC/ML/data/machine-data.csv
ashborn/data/ML TS XAI HC/ML/data/wine-dataset.csv
ashborn/data/ML TS XAI HC/TS/1. EDA - Handling Time Series Data.ipynb
ashborn/data/ML TS XAI HC/TS/2. Feature Engineering.ipynb
ashborn/data/ML TS XAI HC/TS/3. Temporal Relationships.ipynb
ashborn/data/ML TS XAI HC/TS/4. Up-Down-Sampling and Interpolation.ipynb
ashborn/data/ML TS XAI HC/TS/5. Stationarity - Trend - Seasonality.ipynb
ashborn/data/ML TS XAI HC/TS/6. Autocorrelation - Partial Autocorrelation.ipynb
ashborn/data/ML TS XAI HC/TS/AllinOne.ipynb
ashborn/data/ML TS XAI HC/TS/data/daily-min-temperatures.csv
ashborn/data/ML TS XAI HC/TS/data/daily-total-female-births.csv
ashborn/data/ML TS XAI HC/TS/data/raw_sales.csv
ashborn/data/ML TS XAI HC/TS/data/shampoo_sales.csv
ashborn/utils/__init__.py
ashborn/utils/shell_utils.py
ashborn-0.1.dist-info/licenses/LICENSE.txt
ashborn-0.1.dist-info/METADATA
ashborn-0.1.dist-info/WHEEL
ashborn-0.1.dist-info/top_level.txt
ashborn-0.1.dist-info/RECORD
